zabbix_multisender-0.4.7.dist-info/DESCRIPTION.rst
zabbix_multisender-0.4.7.dist-info/METADATA
zabbix_multisender-0.4.7.dist-info/RECORD
zabbix_multisender-0.4.7.dist-info/WHEEL
zabbix_multisender-0.4.7.dist-info/entry_points.txt
zabbix_multisender-0.4.7.dist-info/metadata.json
zabbix_multisender-0.4.7.dist-info/top_level.txt
zms/__init__.py
